{
  "_comment": "Starter condo map. LAYOUT IS PLACEHOLDER — to be redrawn against Unreal prototype screenshots for parity (Phase 1 reference). All coordinates and asset footprints are meters; gridSize is the nav/map tile size and snapStep is placement precision. navGrid is derived at load.",
  "id": "condo",
  "name": "condo",
  "propertyType": "basement",
  "gridSize": 0.25,
  "snapStep": 0.25,
  "bounds": {
    "w": 6,
    "h": 9
  },
  "floors": [
    {
      "id": "floor_1",
      "polygon": [
        [
          0,
          0
        ],
        [
          4,
          0
        ],
        [
          4,
          5
        ],
        [
          0,
          5
        ]
      ],
      "material": "wood",
      "texture": "textures/ShittyFloor.jpg"
    },
    {
      "id": "floor_2",
      "polygon": [
        [
          4,
          0
        ],
        [
          6,
          0
        ],
        [
          6,
          4
        ],
        [
          4,
          4
        ]
      ],
      "material": "tile",
      "texture": "textures/ShittyTiling.jpg"
    },
    {
      "id": "floor_3",
      "polygon": [
        [
          0,
          5
        ],
        [
          4,
          5
        ],
        [
          4,
          7
        ],
        [
          0,
          7
        ]
      ],
      "material": "carpet",
      "texture": "textures/Carpet1.jpg"
    },
    {
      "id": "floor_4",
      "polygon": [
        [
          4,
          4
        ],
        [
          6,
          4
        ],
        [
          6,
          7
        ],
        [
          4,
          7
        ]
      ],
      "material": "tile",
      "texture": "textures/ChineseTiles.jpg"
    }
  ],
  "walls": [
    {
      "from": [
        0,
        7
      ],
      "to": [
        0,
        0
      ],
      "texture": "textures/wallpaint.jpg",
      "textureB": "textures/Concrete.jpg"
    },
    {
      "from": [
        6,
        4
      ],
      "to": [
        4,
        4
      ],
      "textureB": "textures/ShittyTiling2.jpg",
      "texture": "textures/Tiling.jpg"
    },
    {
      "from": [
        6,
        4
      ],
      "to": [
        6,
        0
      ],
      "texture": "textures/Concrete.jpg",
      "textureB": "textures/ShittyTiling2.jpg"
    },
    {
      "from": [
        6,
        0
      ],
      "to": [
        0,
        0
      ],
      "texture": "textures/wallpaint.jpg",
      "textureB": "textures/Concrete.jpg"
    },
    {
      "from": [
        6,
        7
      ],
      "to": [
        0,
        7
      ],
      "texture": "textures/Concrete.jpg",
      "textureB": "textures/wallpaper.jpg"
    },
    {
      "from": [
        3,
        1
      ],
      "to": [
        3,
        0
      ],
      "texture": "textures/ShittyTiling2.jpg",
      "textureB": "textures/wallpaint.jpg"
    },
    {
      "from": [
        4,
        7
      ],
      "to": [
        4,
        4
      ],
      "texture": "textures/Tiling.jpg",
      "textureB": "textures/wallpaint.jpg"
    },
    {
      "from": [
        6,
        4
      ],
      "to": [
        6,
        7
      ],
      "texture": "textures/Concrete.jpg",
      "textureB": "textures/Tiling.jpg"
    }
  ],
  "doors": [
    {
      "at": [
        0,
        2.17
      ],
      "orientation": "vertical",
      "assetId": "door_exterior",
      "_note": "ROADMAP_NEXT item 9 — apartment entrance, exterior door (living room outer wall). Static/tappable, never auto-opens."
    },
    {
      "at": [
        4,
        5.75
      ],
      "orientation": "vertical",
      "assetId": "door_basic"
    }
  ],
  "windows": [
    {
      "at": [
        1.25,
        7
      ],
      "orientation": "horizontal",
      "assetId": "window_basic",
      "width": 0.5
    }
  ],
  "spawn": {
    "pos": [
      0.5,
      2.25
    ],
    "facingDeg": 90
  },
  "placedObjects": [
    {
      "asset": "shower",
      "pos": [
        4.5,
        4.5
      ],
      "rotDeg": 0
    },
    {
      "asset": "sink",
      "pos": [
        5.5,
        4.5
      ],
      "rotDeg": 0
    },
    {
      "asset": "dining_table",
      "pos": [
        4,
        0.5
      ],
      "rotDeg": 0
    },
    {
      "asset": "dining_chair",
      "pos": [
        3.5,
        1.5
      ],
      "rotDeg": 180
    },
    {
      "asset": "stove",
      "pos": [
        5.565,
        2.625
      ],
      "rotDeg": 270
    },
    {
      "asset": "bookshelf",
      "pos": [
        1.5,
        0.25
      ],
      "rotDeg": 0
    },
    {
      "asset": "garbage_can",
      "pos": [
        5.69,
        1
      ],
      "rotDeg": 270
    },
    {
      "asset": "armchair",
      "pos": [
        2.25,
        3.75
      ],
      "rotDeg": 270
    },
    {
      "asset": "lamp",
      "pos": [
        3.75,
        6.75
      ],
      "rotDeg": 180
    },
    {
      "asset": "wall_lamp",
      "pos": [
        5.5,
        0.14
      ],
      "rotDeg": 0
    },
    {
      "asset": "wall_lamp",
      "pos": [
        0.14,
        1
      ],
      "rotDeg": 90
    },
    {
      "asset": "wall_lamp",
      "pos": [
        5.86,
        5.5
      ],
      "rotDeg": 270
    },
    {
      "asset": "tv",
      "pos": [
        0.185,
        3.75
      ],
      "rotDeg": 90
    },
    {
      "asset": "water_puddle",
      "pos": [
        4,
        2.75
      ],
      "rotDeg": 0
    },
    {
      "asset": "water_puddle",
      "pos": [
        1.25,
        2
      ],
      "rotDeg": 0
    },
    {
      "asset": "water_puddle",
      "pos": [
        2.5,
        2.5
      ],
      "rotDeg": 0
    },
    {
      "asset": "water_puddle",
      "pos": [
        2.5,
        1.25
      ],
      "rotDeg": 0
    },
    {
      "asset": "water_puddle",
      "pos": [
        4.75,
        5.5
      ],
      "rotDeg": 0
    },
    {
      "asset": "water_puddle",
      "pos": [
        3.25,
        5.25
      ],
      "rotDeg": 0
    },
    {
      "asset": "stinky_fridge",
      "pos": [
        5.5,
        3.5
      ],
      "rotDeg": 270
    },
    {
      "asset": "kitchen_sink",
      "pos": [
        5.69,
        1.75
      ],
      "rotDeg": 270
    },
    {
      "asset": "rustic_bed",
      "pos": [
        1.06,
        5.75
      ],
      "rotDeg": 90
    },
    {
      "asset": "basement_toilet",
      "pos": [
        5.5,
        6.44
      ],
      "rotDeg": 270
    }
  ],
  "music": [
    "sounds/music_condo_2.mp3"
  ]
}