{
  "fonts": {
    "family": "Loucos Lyne",
    "sizePx": 12,
    "faces": [
      {
        "family": "Loucos Lyne",
        "src": "/fonts/Loucos Lyne - thesimssansbold.otf",
        "weight": "700",
        "style": "normal"
      },
      {
        "family": "Loucos Lyne Small Caps",
        "src": "/fonts/Loucos Lyne - thesimssansboldsc.otf",
        "weight": "700",
        "style": "normal"
      }
    ]
  },
  "colors": {
    "panelBg": "#5e5ee8",
    "panelFg": "#dfe6f2",
    "accent": "rgba(90,120,190,.55)",
    "warn": "#e0b05f",
    "error": "#e57a7a",
    "buttonBg": "#bbd0f2",
    "buttonFg": "#eaf0fb",
    "outline": "#ffffff"
  },
  "shapes": {
    "radiusPx": 8,
    "outlineWidthPx": 2,
    "shadow": "0 3px 14px rgba(0,0,0,.35)"
  },
  "components": {
    "panel": {
      "background": "rgba(20,26,40,.82)",
      "foreground": "#dfe6f2",
      "radiusPx": 18,
      "shadow": "none",
      "fontFamily": "Loucos Lyne",
      "fontSizePx": 9
    },
    "button": {
      "background": "#c7a4f2",
      "foreground": "#eaf0fb",
      "accent": "rgba(90,120,190,.4)",
      "outline": "rgba(90,120,190,.4)",
      "radiusPx": 999,
      "outlineWidthPx": 0,
      "shadow": "none",
      "fontFamily": "Loucos Lyne"
    },
    "toast": {
      "background": "rgba(20,26,40,.92)",
      "foreground": "#eaf0fb",
      "accent": "#5a9fd6",
      "radiusPx": 16,
      "outlineWidthPx": -1,
      "shadow": "0 2px 10px rgba(0,0,0,.35)",
      "fontSizePx": 9,
      "fontFamily": "Loucos Lyne"
    },
    "actionMenu": {
      "background": "#dfe6f2",
      "foreground": "rgba(0,0,0,0.75)",
      "accent": "rgba(90,120,190,.4)",
      "outline": "rgba(0,0,0,0.75)",
      "radiusPx": 13,
      "outlineWidthPx": 0,
      "shadow": "0 4px 16px rgba(0,0,0,.4)",
      "fontSizePx": 10,
      "fontFamily": "Loucos Lyne",
      "marginPx": 0,
      "paddingXPx": 3,
      "paddingYPx": 2,
      "widthPx": 102,
      "heightPx": 26,
      "centerRadiusPx": 120
    },
    "card": {
      "radiusPx": 10
    },
    "bar": {
      "background": "rgba(255,255,255,.10)",
      "radiusPx": 7,
      "heightPx": 14
    },
    "phoneShell": {
      "radiusPx": 30,
      "outlineWidthPx": 2
    },
    "phoneTab": {
      "radiusPx": 999,
      "paddingXPx": 3,
      "paddingYPx": 7,
      "heightPx": 48
    },
    "accordionHeader": {
      "radiusPx": 999,
      "paddingXPx": 11,
      "paddingYPx": 7
    },
    "titleScreen": {
      "background": "rgba(20,26,40,.88)",
      "foreground": "#eaf0fb",
      "accent": "#9fd08c",
      "outline": "rgba(130,158,210,.55)",
      "outlineWidthPx": 1,
      "shadow": "0 10px 40px rgba(0,0,0,.45)",
      "fontSizePx": 10
    },
    "notificationCard": {
      "background": "rgba(20,26,40,.92)",
      "foreground": "#eaf0fb",
      "accent": "#5a9fd6",
      "outline": "rgba(130,158,210,.45)",
      "radiusPx": 10,
      "outlineWidthPx": 2,
      "shadow": "0 2px 10px rgba(0,0,0,.35)",
      "fontSizePx": 9,
      "fontFamily": "Loucos Lyne"
    },
    "notificationModal": {
      "background": "rgba(20,26,40,.96)",
      "foreground": "#eaf0fb",
      "accent": "#5a9fd6",
      "outline": "rgba(130,158,210,.55)",
      "radiusPx": 18,
      "outlineWidthPx": 2,
      "shadow": "0 10px 40px rgba(0,0,0,.55)",
      "fontSizePx": 11,
      "fontFamily": "Loucos Lyne"
    }
  },
  "layout": {
    "needs-panel": {
      "anchor": "tl",
      "offsetX": 5,
      "offsetY": 5,
      "accordion": "Needs"
    },
    "skills-panel": {
      "anchor": "tr",
      "offsetX": 5,
      "offsetY": 5,
      "accordion": "Skills"
    },
    "quest-panel": {
      "anchor": "bl",
      "offsetX": 5,
      "offsetY": 5,
      "accordion": "Needs"
    },
    "time-bar": {
      "anchor": "bc",
      "offsetX": 0,
      "offsetY": 5
    },
    "activity-chip": {
      "anchor": "bc",
      "offsetX": 0,
      "offsetY": 120
    },
    "work-chip": {
      "anchor": "bc",
      "offsetX": 0,
      "offsetY": 120
    },
    "notification-stack": {
      "anchor": "tc",
      "offsetX": 0,
      "offsetY": 66
    },
    "visa-chip": {
      "anchor": "bl",
      "offsetX": 5,
      "offsetY": 60
    },
    "funds-chip": {
      "anchor": "bl",
      "offsetX": 5,
      "offsetY": 5
    },
    "buy-button": {
      "anchor": "br",
      "offsetX": 5,
      "offsetY": 5
    },
    "wall-cut-button": {
      "anchor": "br",
      "offsetX": 5,
      "offsetY": 55
    },
    "phone-button": {
      "anchor": "bc",
      "offsetX": 0,
      "offsetY": 50
    },
    "system-menu-button": {
      "anchor": "tc",
      "offsetX": 5,
      "offsetY": 5
    },
    "buy-ghost-controls": {
      "anchor": "bc",
      "offsetX": 0,
      "offsetY": 14
    },
    "buy-selection-chips": {
      "anchor": "bc",
      "offsetX": 0,
      "offsetY": 14
    }
  },
  "accordions": [
    {
      "name": "Needs",
      "collapsedByDefault": true,
      "icon": "/icons/needs.svg",
      "showText": false,
      "happinessHeader": true
    },
    {
      "name": "Skills",
      "collapsedByDefault": true,
      "icon": "/icons/skills.svg",
      "showText": false
    }
  ]
}
